calculator_gabija2022/__init__.py
calculator_gabija2022/calculator_main.py
calculator_gabija2022-1.0.0.dist-info/LICENSE.txt
calculator_gabija2022-1.0.0.dist-info/METADATA
calculator_gabija2022-1.0.0.dist-info/WHEEL
calculator_gabija2022-1.0.0.dist-info/top_level.txt
calculator_gabija2022-1.0.0.dist-info/RECORD
